officeasy/__init__.py
officeasy-0.0.3.dist-info/LICENSE
officeasy-0.0.3.dist-info/METADATA
officeasy-0.0.3.dist-info/WHEEL
officeasy-0.0.3.dist-info/top_level.txt
officeasy-0.0.3.dist-info/RECORD
